utoolbox/cli/__init__.py
utoolbox/cli/am2csv.py
utoolbox/cli/aszarr.py
utoolbox/cli/deskew.py
utoolbox/cli/mm2bdv.py
utoolbox/cli/stacks.py
utoolbox/cli/utils.py
utoolbox/cli/converter/__init__.py
utoolbox/cli/converter/mm2bdv.py
utoolbox/cli/dataset/__init__.py
utoolbox/cli/dataset/edit.py
utoolbox/cli/dataset/export.py
utoolbox/cli/dataset/info.py
utoolbox/cli/dataset/main.py
utoolbox/cli/dataset/preview.py
utoolbox/cli/dataset/pyramid.py
utoolbox/cli/dataset/scan.py
utoolbox/cli/dataset/transform.py
utoolbox/cli/prompt/__init__.py
utoolbox/cli/prompt/options.py
utoolbox/cli/prompt/simple.py
utoolbox/cli/prompt/validators.py
utoolbox/cli_deprecate/__init__.py
utoolbox/cli_deprecate/am2csv.py
utoolbox/cli_deprecate/deskew.py
utoolbox/cli_deprecate/mm2bdv.py
utoolbox/cli_deprecate/stacks.py
utoolbox/cli_deprecate/utils.py
utoolbox/cli_deprecate/dataset/__init__.py
utoolbox/cli_deprecate/dataset/export.py
utoolbox/cli_deprecate/dataset/main.py
utoolbox/cli_deprecate/dataset/preview.py
utoolbox/cli_deprecate/dataset/scan.py
utoolbox/cli_deprecate/dataset/transform.py
utoolbox/cli_deprecate/prompt/__init__.py
utoolbox/cli_deprecate/prompt/options.py
utoolbox/cli_deprecate/prompt/simple.py
utoolbox/cli_deprecate/prompt/validators.py
utoolbox/data/__init__.py
utoolbox/data/dataset/__init__.py
utoolbox/data/dataset/base.py
utoolbox/data/dataset/error.py
utoolbox/data/dataset/bdv/__init__.py
utoolbox/data/dataset/bdv/dataset.py
utoolbox/data/dataset/imaris/__init__.py
utoolbox/data/dataset/imaris/dataset.py
utoolbox/data/dataset/imaris/error.py
utoolbox/data/dataset/mm/__init__.py
utoolbox/data/dataset/mm/dataset.py
utoolbox/data/dataset/mm/error.py
utoolbox/data/dataset/spim/__init__.py
utoolbox/data/dataset/spim/dataset.py
utoolbox/data/dataset/spim/error.py
utoolbox/data/dataset/spim/settings.py
utoolbox/data/dataset/spim/utils.py
utoolbox/data/datastore/__init__.py
utoolbox/data/datastore/base.py
utoolbox/data/datastore/direct.py
utoolbox/data/datastore/error.py
utoolbox_core-0.0.22.dist-info/LICENSE.md
utoolbox_core-0.0.22.dist-info/METADATA
utoolbox_core-0.0.22.dist-info/WHEEL
utoolbox_core-0.0.22.dist-info/entry_points.txt
utoolbox_core-0.0.22.dist-info/top_level.txt
utoolbox_core-0.0.22.dist-info/zip-safe
utoolbox_core-0.0.22.dist-info/RECORD
