Metadata-Version: 2.1
Name: utoolbox-core
Version: 0.0.22
Summary: Core functions for uToolbox.
Home-page: https://github.com/liuyenting/utoolbox-core
Author: Liu, Yen-Ting
License: UNKNOWN
Keywords: microscopy
Platform: UNKNOWN
Classifier: Development Status :: 3 - Alpha
Classifier: License :: OSI Approved :: Apache Software License
Classifier: Operating System :: MacOS
Classifier: Operating System :: Microsoft :: Windows
Classifier: Operating System :: POSIX :: Linux
Classifier: Programming Language :: Python :: 3
Classifier: Topic :: Scientific/Engineering
Classifier: Intended Audience :: Developers
Classifier: Intended Audience :: End Users/Desktop
Classifier: Intended Audience :: Science/Research
Requires-Python: ~=3.7
Requires-Dist: click
Requires-Dist: coloredlogs
Requires-Dist: dask[complete] (~=2.20.0)
Requires-Dist: dask-jobqueue
Requires-Dist: distributed (~=2.20.0)
Requires-Dist: h5py (>=2.9)
Requires-Dist: humanfriendly
Requires-Dist: imageio[ffmpeg]
Requires-Dist: natsort
Requires-Dist: numpy (>=1.17)
Requires-Dist: pandas
Requires-Dist: prompt-toolkit (>=3.0)
Requires-Dist: tifffile
Requires-Dist: xxhash
Requires-Dist: zarr
Provides-Extra: gpu
Requires-Dist: cupy-cuda101 ; extra == 'gpu'
Provides-Extra: original
Requires-Dist: mako ; extra == 'original'
Requires-Dist: tqdm ; extra == 'original'
Provides-Extra: viewer
Requires-Dist: napari ; extra == 'viewer'
